{
  "teams": [
    {
      "id": 1,
      "name": "FC Barcelona",
      "coach": "Ernesto Valverde",
      "description": "The best football team in the world!"
    },
    {
      "id": 2,
      "name": "Real Madrid",
      "coach": "Zinedine Zidane",
      "description": "The worst football team in the world!"
    }
  ],
  "users": [
    {
      "id": 1,
      "firstName": "Anil",
      "lastName": "Bansode",
      "userName": "anilb",
      "age": "29",
      "salary": "24000",
      "isAdmin": false
    },
    {
      "username": "pravinm",
      "password": "Welcome@123",
      "id": 2
    }
  ]
}